micropython_mmr902/__init__.py
micropython_mmr902/mmr902.py
micropython_mmr902-0.1.0.dist-info/LICENSE
micropython_mmr902-0.1.0.dist-info/METADATA
micropython_mmr902-0.1.0.dist-info/WHEEL
micropython_mmr902-0.1.0.dist-info/top_level.txt
micropython_mmr902-0.1.0.dist-info/RECORD
