Metadata-Version: 2.1
Name: micropython-mmr902
Version: 0.1.0
Summary: MicroPython Driver fro the Mitsumi MMR902 Micro Pressure Sensor
Author-email: JDM <xxyx@mailmeto.mozmail.com>
License: MIT
Project-URL: Homepage, https://github.com/jposada202020/MicroPython_MMR902
Keywords: sensor,micropython,mmr902,pressure,micropython,mitsumi,mmr902,driver,sensor
Classifier: Intended Audience :: Developers
Classifier: Topic :: Software Development :: Libraries
Classifier: Topic :: Software Development :: Embedded Systems
Classifier: Topic :: System :: Hardware
Classifier: License :: OSI Approved :: MIT License
Classifier: Programming Language :: Python :: Implementation :: MicroPython
License-File: LICENSE
